aiotnse/__init__.py
aiotnse/__main__.py
aiotnse/_version.py
aiotnse/api.py
aiotnse/auth.py
aiotnse/cli.py
aiotnse/const.py
aiotnse/exceptions.py
aiotnse/helpers.py
aiotnse/py.typed
aiotnse-1.3.0.dist-info/LICENSE
aiotnse-1.3.0.dist-info/METADATA
aiotnse-1.3.0.dist-info/WHEEL
aiotnse-1.3.0.dist-info/entry_points.txt
aiotnse-1.3.0.dist-info/top_level.txt
aiotnse-1.3.0.dist-info/RECORD
